setup.cfg
setup.py
pgrap/__init__.py
pgrap/pgdoc.py
pgrap/pgkv.py
pgrap/pgrap.py
pgrap.egg-info/PKG-INFO
pgrap.egg-info/SOURCES.txt
pgrap.egg-info/dependency_links.txt
pgrap.egg-info/requires.txt
pgrap.egg-info/top_level.txt