Metadata-Version: 1.1
Name: pgrap
Version: 0.5
Summary: Postgres library for key-value and document style db access
Home-page: https://github.com/bobcolner/pgrap
Author: Bob Colner
Author-email: bcolner@gmail.com
License: MIT
Download-URL: https://github.com/bobcolner/pgrap/tarball/0.5
Keywords: postgres,sql,key-value
Platform: any
Classifier: Development Status :: 3 - Alpha
Classifier: Intended Audience :: Developers
Classifier: Topic :: Database :: Front-Ends    
Classifier: License :: OSI Approved :: MIT License
Classifier: Programming Language :: Python :: 3.3
Classifier: Programming Language :: Python :: 3.4
Classifier: Programming Language :: Python :: 3.5
